odoo/addons/product_variant_multi_link/README.rst
odoo/addons/product_variant_multi_link/__init__.py
odoo/addons/product_variant_multi_link/__manifest__.py
odoo/addons/product_variant_multi_link/i18n/es_AR.po
odoo/addons/product_variant_multi_link/i18n/nl.po
odoo/addons/product_variant_multi_link/i18n/product_variant_multi_link.pot
odoo/addons/product_variant_multi_link/models/__init__.py
odoo/addons/product_variant_multi_link/models/product_product.py
odoo/addons/product_variant_multi_link/models/product_template_link.py
odoo/addons/product_variant_multi_link/readme/CONTRIBUTORS.rst
odoo/addons/product_variant_multi_link/readme/CREDITS.rst
odoo/addons/product_variant_multi_link/readme/DESCRIPTION.rst
odoo/addons/product_variant_multi_link/readme/USAGE.rst
odoo/addons/product_variant_multi_link/static/description/icon.png
odoo/addons/product_variant_multi_link/static/description/index.html
odoo/addons/product_variant_multi_link/tests/__init__.py
odoo/addons/product_variant_multi_link/tests/test_product_template_link.py
odoo/addons/product_variant_multi_link/views/product_product_view.xml
odoo/addons/product_variant_multi_link/views/product_template_link_view.xml
odoo14_addon_product_variant_multi_link-14.0.1.1.0.dist-info/METADATA
odoo14_addon_product_variant_multi_link-14.0.1.1.0.dist-info/WHEEL
odoo14_addon_product_variant_multi_link-14.0.1.1.0.dist-info/top_level.txt
odoo14_addon_product_variant_multi_link-14.0.1.1.0.dist-info/RECORD
